flask_compose/__init__.py
tests/__init__.py
tests/include_tests.py
tests/route_tests.py
tests/router_tests.py
tests/type_tests.py
flask_compose-0.2.0.dist-info/LICENSE
flask_compose-0.2.0.dist-info/METADATA
flask_compose-0.2.0.dist-info/WHEEL
flask_compose-0.2.0.dist-info/top_level.txt
flask_compose-0.2.0.dist-info/RECORD
