Metadata-Version: 2.1
Name: flask-compose
Version: 0.2.0
Summary: A routing library for flask applications obeying the "Decorator Design Pattern".
Home-page: https://github.com/cmanallen/flask_router
Author: Colton Allen
Author-email: colton.allen@caxiam.com
License: UNKNOWN
Platform: UNKNOWN
Classifier: Programming Language :: Python :: 3
Classifier: License :: OSI Approved :: MIT License
Classifier: Operating System :: OS Independent
Requires-Dist: flask
